dd_snovio
