Metadata-Version: 2.1
Name: dd-snovio
Version: 0.2
Summary: A Python library designed to simplify work with the snovio API
Home-page: UNKNOWN
Author: DevsData
Author-email: tpotanski@devsdata.com
License: MIT
Keywords: snovio,snovio api,devsdata
Platform: UNKNOWN
Classifier: Development Status :: 3 - Alpha
Classifier: Intended Audience :: Developers
Classifier: Topic :: Software Development :: Build Tools
Classifier: License :: OSI Approved :: MIT License
Classifier: Programming Language :: Python :: 3.7
Classifier: Programming Language :: Python :: 3.8
Classifier: Programming Language :: Python :: 3.9
License-File: LICENSE
